src/main.py
src/api/__api__.py
src/api/__init__.py
src/api/chatroom.py
src/api/redpacket.py
src/api/user.py
src/core/__init__.py
src/core/blacklist.py
src/core/chatroom.py
src/core/command.py
src/core/config.py
src/core/redpacket.py
src/core/user.py
src/core/websocket.py
src/utils/utils.py
src/utils/version.py
pwl_chat_python-1.5.3.dist-info/LICENSE
pwl_chat_python-1.5.3.dist-info/METADATA
pwl_chat_python-1.5.3.dist-info/WHEEL
pwl_chat_python-1.5.3.dist-info/entry_points.txt
pwl_chat_python-1.5.3.dist-info/top_level.txt
pwl_chat_python-1.5.3.dist-info/RECORD
