Metadata-Version: 2.1
Name: pwl-chat-python
Version: 1.5.3
Summary: 摸鱼派聊天室python客户端
Home-page: https://github.com/gakkiyomi/pwl-chat-python
Author: gakkiyomi
Author-email: gakkiyomi@gmail.com
License: MIT
Platform: UNKNOWN
Classifier: License :: OSI Approved :: MIT License
Classifier: Programming Language :: Python
Classifier: Programming Language :: Python :: 3.10
Classifier: Programming Language :: Python :: Implementation :: CPython
Classifier: Programming Language :: Python :: Implementation :: PyPy
Requires-Python: >=3.9
License-File: LICENSE
Requires-Dist: requests
Requires-Dist: websocket-client
Requires-Dist: click
Requires-Dist: schedule
